LICENSE
MANIFEST.in
README
README.md
pyproject.toml
setup.cfg
setup.py
pyiArduinoI2Ckeyboard/WString.cpp
pyiArduinoI2Ckeyboard/WString.h
pyiArduinoI2Ckeyboard/__init__.py
pyiArduinoI2Ckeyboard/dtostrf.cpp
pyiArduinoI2Ckeyboard/dtostrf.h
pyiArduinoI2Ckeyboard/iarduino_I2C_Keyboard.cpp
pyiArduinoI2Ckeyboard/iarduino_I2C_Keyboard.h
pyiArduinoI2Ckeyboard/iarduino_I2C_Keyboard.pxd
pyiArduinoI2Ckeyboard/iarduino_I2C_PI.cpp
pyiArduinoI2Ckeyboard/iarduino_I2C_PI.h
pyiArduinoI2Ckeyboard/itoa.cpp
pyiArduinoI2Ckeyboard/itoa.h
pyiArduinoI2Ckeyboard/pyiArduinoI2Ckeyboard.cpp
pyiArduinoI2Ckeyboard/pyiArduinoI2Ckeyboard.pyx
pyiArduinoI2Ckeyboard/setup.py
pyiArduinoI2Ckeyboard/cpp/FindDevices.cpp
pyiArduinoI2Ckeyboard/cpp/NewAddress.cpp
pyiArduinoI2Ckeyboard/cpp/Serial.h
pyiArduinoI2Ckeyboard/cpp/getAllKeyState.cpp
pyiArduinoI2Ckeyboard/cpp/getKeyState.cpp
pyiArduinoI2Ckeyboard/cpp/getTime.cpp
pyiArduinoI2Ckeyboard/cpp/main.cpp
pyiArduinoI2Ckeyboard/cpp/printChar.cpp
pyiArduinoI2Ckeyboard/cpp/printString.cpp
pyiArduinoI2Ckeyboard/cpp/setAllLed_KeyState.cpp
pyiArduinoI2Ckeyboard/cpp/setAnimation.cpp
pyiArduinoI2Ckeyboard/cpp/setLed.cpp
pyiArduinoI2Ckeyboard/cpp/setLed_KeyState.cpp
pyiArduinoI2Ckeyboard/cpp/setLight.cpp
pyiArduinoI2Ckeyboard/cpp/setSettings.cpp
pyiArduinoI2Ckeyboard/examples/FindDevices.py
pyiArduinoI2Ckeyboard/examples/getAllKeyState.py
pyiArduinoI2Ckeyboard/examples/getKeyState.py
pyiArduinoI2Ckeyboard/examples/getTime.py
pyiArduinoI2Ckeyboard/examples/newAddress.py
pyiArduinoI2Ckeyboard/examples/printChar.py
pyiArduinoI2Ckeyboard/examples/printString.py
pyiArduinoI2Ckeyboard/examples/setAllLed_KeyState.py
pyiArduinoI2Ckeyboard/examples/setAnimation.py
pyiArduinoI2Ckeyboard/examples/setLed.py
pyiArduinoI2Ckeyboard/examples/setLed_KeyState.py
pyiArduinoI2Ckeyboard/examples/setLight.py
pyiArduinoI2Ckeyboard/examples/setSettings.py
src/pyiArduinoI2Ckeyboard.egg-info/PKG-INFO
src/pyiArduinoI2Ckeyboard.egg-info/SOURCES.txt
src/pyiArduinoI2Ckeyboard.egg-info/dependency_links.txt
src/pyiArduinoI2Ckeyboard.egg-info/top_level.txt
src/pyiarduinoi2ckeyboard/__init__.py