Metadata-Version: 2.1
Name: pyiArduinoI2Ckeyboard
Version: 0.2.1
Summary: iarduino.ru module for Raspberry Pi
Author-email: dron distortion <cancelbutton@gmail.com>
License: MIT
Requires-Python: >=3.11
License-File: LICENSE
